clipassman/__init__.py
clipassman/app_manager.py
clipassman/clipassman.py
clipassman/config.py
clipassman/smart_printer.py
clipassman-2.1.4.dist-info/licenses/LICENSE
smartpasslib/__init__.py
smartpasslib/factories/__init__.py
smartpasslib/factories/smart_password_factory.py
smartpasslib/generators/__init__.py
smartpasslib/generators/base.py
smartpasslib/generators/code.py
smartpasslib/generators/hash.py
smartpasslib/generators/key.py
smartpasslib/generators/smart.py
smartpasslib/generators/strong.py
smartpasslib/generators/urandom.py
smartpasslib/managers/__init__.py
smartpasslib/managers/smart_password_manager.py
smartpasslib/masters/__init__.py
smartpasslib/masters/smart_password_master.py
smartpasslib/smart_passwords/__init__.py
smartpasslib/smart_passwords/smart_password.py
smartpasslib/utils/__init__.py
smartpasslib/utils/decorators.py
clipassman-2.1.4.dist-info/METADATA
clipassman-2.1.4.dist-info/WHEEL
clipassman-2.1.4.dist-info/entry_points.txt
clipassman-2.1.4.dist-info/top_level.txt
clipassman-2.1.4.dist-info/RECORD
