Metadata-Version: 2.4
Name: clipassman
Version: 2.1.4
Summary: Terminal-based smart password manager with deterministic password generation. Generate, manage, and retrieve passwords without storing them - all from your command line.
Author-email: Alexander Suvorov <smartlegiondev@gmail.com>
License-Expression: BSD-3-Clause
Project-URL: Homepage, https://github.com/smartlegionlab/clipassman
Classifier: Programming Language :: Python :: 3
Classifier: Programming Language :: Python :: 3.7
Classifier: Programming Language :: Python :: 3.8
Classifier: Programming Language :: Python :: 3.9
Classifier: Programming Language :: Python :: 3.10
Classifier: Programming Language :: Python :: 3.11
Classifier: Programming Language :: Python :: 3.12
Classifier: Operating System :: OS Independent
Classifier: Topic :: Security
Classifier: Intended Audience :: End Users/Desktop
Classifier: Environment :: Console
Requires-Python: >=3.6
License-File: LICENSE
Dynamic: license-file
